.bumpversion.cfg
.cookiecutterrc
.coveragerc
.editorconfig
.pre-commit-config.yaml
.readthedocs.yml
AUTHORS.rst
CHANGELOG.rst
CONTRIBUTING.rst
MANIFEST.in
README.rst
pyproject.toml
pytest.ini
setup.py
tox.ini
.github/workflows/github-actions.yml
ci/bootstrap.py
ci/requirements.txt
ci/templates/.github/workflows/github-actions.yml
docs/authors.rst
docs/changelog.rst
docs/conf.py
docs/contributing.rst
docs/index.rst
docs/installation.rst
docs/readme.rst
docs/requirements.txt
docs/spelling_wordlist.txt
docs/usage.rst
docs/reference/bakabaka.rst
docs/reference/index.rst
src/bakabaka/__init__.py
src/bakabaka/__main__.py
src/bakabaka/cli.py
src/bakabaka.egg-info/PKG-INFO
src/bakabaka.egg-info/SOURCES.txt
src/bakabaka.egg-info/dependency_links.txt
src/bakabaka.egg-info/entry_points.txt
src/bakabaka.egg-info/not-zip-safe
src/bakabaka.egg-info/requires.txt
src/bakabaka.egg-info/top_level.txt
tests/test_bakabaka.py