Metadata-Version: 2.1
Name: bakabaka
Version: 0.0.0
Summary: bakabaka ai common for someone who really know it's value
Home-page: https://github.com/luzhongqiu/bakabaka
Author: Nic Lu
Author-email: zq.lu@foxmail.com
Project-URL: Documentation, https://bakabaka.readthedocs.io/
Project-URL: Changelog, https://bakabaka.readthedocs.io/en/latest/changelog.html
Project-URL: Issue Tracker, https://github.com/nic/bakabaka/issues
Classifier: Development Status :: 5 - Production/Stable
Classifier: Intended Audience :: Developers
Classifier: Operating System :: Unix
Classifier: Operating System :: POSIX
Classifier: Operating System :: Microsoft :: Windows
Classifier: Programming Language :: Python
Classifier: Programming Language :: Python :: 3
Classifier: Programming Language :: Python :: 3 :: Only
Classifier: Programming Language :: Python :: 3.8
Classifier: Programming Language :: Python :: 3.9
Classifier: Programming Language :: Python :: 3.10
Classifier: Programming Language :: Python :: 3.11
Classifier: Programming Language :: Python :: 3.12
Classifier: Programming Language :: Python :: Implementation :: CPython
Classifier: Programming Language :: Python :: Implementation :: PyPy
Classifier: Topic :: Utilities
Requires-Python: >=3.8
License-File: AUTHORS.rst
Requires-Dist: click
